[
  {
    "peak_date": "2019-05-12T07:59:59Z",
    "peak_nav": 13761.52,
    "trough_date": "2019-05-12T15:59:59Z",
    "trough_nav": 12629.79,
    "recovery_date": "2019-05-13T15:59:59Z",
    "drawdown_pct": 8.22,
    "bars_to_trough": 2,
    "bars_to_recovery": 8,
    "days_to_trough": 0.3,
    "days_to_recovery": 1.3
  },
  {
    "peak_date": "2019-05-14T07:59:59Z",
    "peak_nav": 15247.52,
    "trough_date": "2019-05-23T07:59:59Z",
    "trough_nav": 13428.15,
    "recovery_date": "2019-05-27T03:59:59Z",
    "drawdown_pct": 11.93,
    "bars_to_trough": 54,
    "bars_to_recovery": 77,
    "days_to_trough": 9.0,
    "days_to_recovery": 12.8
  },
  {
    "peak_date": "2019-05-30T15:59:59Z",
    "peak_nav": 15729.61,
    "trough_date": "2019-06-09T23:59:59Z",
    "trough_nav": 13948.49,
    "recovery_date": "2019-06-15T15:59:59Z",
    "drawdown_pct": 11.32,
    "bars_to_trough": 62,
    "bars_to_recovery": 96,
    "days_to_trough": 10.3,
    "days_to_recovery": 16.0
  },
  {
    "peak_date": "2019-06-26T19:59:59Z",
    "peak_nav": 24956.94,
    "trough_date": "2019-07-30T03:59:59Z",
    "trough_nav": 19958.14,
    "recovery_date": "2019-08-06T07:59:59Z",
    "drawdown_pct": 20.03,
    "bars_to_trough": 200,
    "bars_to_recovery": 243,
    "days_to_trough": 33.3,
    "days_to_recovery": 40.5
  },
  {
    "peak_date": "2019-08-06T07:59:59Z",
    "peak_nav": 25143.93,
    "trough_date": "2019-10-24T03:59:59Z",
    "trough_nav": 19521.71,
    "recovery_date": "2019-10-27T19:59:59Z",
    "drawdown_pct": 22.36,
    "bars_to_trough": 473,
    "bars_to_recovery": 495,
    "days_to_trough": 78.8,
    "days_to_recovery": 82.5
  },
  {
    "peak_date": "2019-10-27T19:59:59Z",
    "peak_nav": 25382.97,
    "trough_date": "2020-07-05T15:59:59Z",
    "trough_nav": 17234.81,
    "recovery_date": "2020-11-05T23:59:59Z",
    "drawdown_pct": 32.1,
    "bars_to_trough": 1511,
    "bars_to_recovery": 2251,
    "days_to_trough": 251.8,
    "days_to_recovery": 375.2
  },
  {
    "peak_date": "2020-11-06T07:59:59Z",
    "peak_nav": 26111.89,
    "trough_date": "2020-11-07T19:59:59Z",
    "trough_nav": 24452.0,
    "recovery_date": "2020-11-09T11:59:59Z",
    "drawdown_pct": 6.36,
    "bars_to_trough": 9,
    "bars_to_recovery": 19,
    "days_to_trough": 1.5,
    "days_to_recovery": 3.2
  },
  {
    "peak_date": "2020-11-24T15:59:59Z",
    "peak_nav": 31958.97,
    "trough_date": "2020-11-26T11:59:59Z",
    "trough_nav": 29099.86,
    "recovery_date": "2020-12-16T11:59:59Z",
    "drawdown_pct": 8.95,
    "bars_to_trough": 11,
    "bars_to_recovery": 131,
    "days_to_trough": 1.8,
    "days_to_recovery": 21.8
  },
  {
    "peak_date": "2020-12-21T07:59:59Z",
    "peak_nav": 38510.68,
    "trough_date": "2020-12-21T11:59:59Z",
    "trough_nav": 36450.16,
    "recovery_date": "2020-12-25T11:59:59Z",
    "drawdown_pct": 5.35,
    "bars_to_trough": 1,
    "bars_to_recovery": 25,
    "days_to_trough": 0.2,
    "days_to_recovery": 4.2
  },
  {
    "peak_date": "2021-01-03T07:59:59Z",
    "peak_nav": 54684.6,
    "trough_date": "2021-01-04T11:59:59Z",
    "trough_nav": 48955.83,
    "recovery_date": "2021-01-06T07:59:59Z",
    "drawdown_pct": 10.48,
    "bars_to_trough": 7,
    "bars_to_recovery": 18,
    "days_to_trough": 1.2,
    "days_to_recovery": 3.0
  },
  {
    "peak_date": "2021-01-08T11:59:59Z",
    "peak_nav": 65239.82,
    "trough_date": "2021-02-07T15:59:59Z",
    "trough_nav": 47788.5,
    "recovery_date": "2021-05-03T07:59:59Z",
    "drawdown_pct": 26.75,
    "bars_to_trough": 181,
    "bars_to_recovery": 689,
    "days_to_trough": 30.2,
    "days_to_recovery": 114.8
  },
  {
    "peak_date": "2021-05-03T07:59:59Z",
    "peak_nav": 65378.84,
    "trough_date": "2021-09-28T23:59:59Z",
    "trough_nav": 51192.57,
    "recovery_date": "2021-10-06T15:59:59Z",
    "drawdown_pct": 21.7,
    "bars_to_trough": 892,
    "bars_to_recovery": 938,
    "days_to_trough": 148.7,
    "days_to_recovery": 156.3
  },
  {
    "peak_date": "2021-10-20T15:59:59Z",
    "peak_nav": 82102.21,
    "trough_date": "2021-10-27T23:59:59Z",
    "trough_nav": 73499.59,
    "recovery_date": "2021-11-09T03:59:59Z",
    "drawdown_pct": 10.48,
    "bars_to_trough": 44,
    "bars_to_recovery": 117,
    "days_to_trough": 7.3,
    "days_to_recovery": 19.5
  },
  {
    "peak_date": "2021-11-09T03:59:59Z",
    "peak_nav": 83138.97,
    "trough_date": "2023-06-15T15:59:59Z",
    "trough_nav": 58601.12,
    "recovery_date": "2023-12-05T19:59:59Z",
    "drawdown_pct": 29.51,
    "bars_to_trough": 3501,
    "bars_to_recovery": 4540,
    "days_to_trough": 583.5,
    "days_to_recovery": 756.7
  },
  {
    "peak_date": "2023-12-09T07:59:59Z",
    "peak_nav": 86411.74,
    "trough_date": "2023-12-18T03:59:59Z",
    "trough_nav": 80062.85,
    "recovery_date": "2024-01-02T03:59:59Z",
    "drawdown_pct": 7.35,
    "bars_to_trough": 53,
    "bars_to_recovery": 143,
    "days_to_trough": 8.8,
    "days_to_recovery": 23.8
  },
  {
    "peak_date": "2024-01-02T07:59:59Z",
    "peak_nav": 87459.45,
    "trough_date": "2024-01-23T19:59:59Z",
    "trough_nav": 76920.65,
    "recovery_date": "2024-02-08T15:59:59Z",
    "drawdown_pct": 12.05,
    "bars_to_trough": 129,
    "bars_to_recovery": 224,
    "days_to_trough": 21.5,
    "days_to_recovery": 37.3
  },
  {
    "peak_date": "2024-03-04T23:59:59Z",
    "peak_nav": 117107.89,
    "trough_date": "2024-03-05T19:59:59Z",
    "trough_nav": 106564.53,
    "recovery_date": "2024-03-08T19:59:59Z",
    "drawdown_pct": 9.0,
    "bars_to_trough": 5,
    "bars_to_recovery": 23,
    "days_to_trough": 0.8,
    "days_to_recovery": 3.8
  },
  {
    "peak_date": "2024-03-13T19:59:59Z",
    "peak_nav": 124980.68,
    "trough_date": "2024-04-17T15:59:59Z",
    "trough_nav": 114929.19,
    "recovery_date": "2024-05-15T19:59:59Z",
    "drawdown_pct": 8.04,
    "bars_to_trough": 209,
    "bars_to_recovery": 378,
    "days_to_trough": 34.8,
    "days_to_recovery": 63.0
  },
  {
    "peak_date": "2024-05-20T23:59:59Z",
    "peak_nav": 135960.3,
    "trough_date": "2024-08-07T19:59:59Z",
    "trough_nav": 89797.08,
    "recovery_date": "2024-11-20T15:59:59Z",
    "drawdown_pct": 33.95,
    "bars_to_trough": 473,
    "bars_to_recovery": 1102,
    "days_to_trough": 78.8,
    "days_to_recovery": 183.7
  },
  {
    "peak_date": "2024-12-05T03:59:59Z",
    "peak_nav": 150069.55,
    "trough_date": "2024-12-05T23:59:59Z",
    "trough_nav": 141643.64,
    "recovery_date": "2024-12-16T03:59:59Z",
    "drawdown_pct": 5.61,
    "bars_to_trough": 5,
    "bars_to_recovery": 66,
    "days_to_trough": 0.8,
    "days_to_recovery": 11.0
  },
  {
    "peak_date": "2024-12-17T03:59:59Z",
    "peak_nav": 153334.03,
    "trough_date": "2024-12-30T15:59:59Z",
    "trough_nav": 138591.02,
    "recovery_date": "2025-01-17T15:59:59Z",
    "drawdown_pct": 9.61,
    "bars_to_trough": 81,
    "bars_to_recovery": 189,
    "days_to_trough": 13.5,
    "days_to_recovery": 31.5
  },
  {
    "peak_date": "2025-01-20T11:59:59Z",
    "peak_nav": 161616.82,
    "trough_date": "2025-04-21T19:59:59Z",
    "trough_nav": 99555.73,
    "recovery_date": null,
    "drawdown_pct": 38.4,
    "bars_to_trough": 548,
    "bars_to_recovery": null,
    "days_to_trough": 91.3,
    "days_to_recovery": null
  }
]